pcap_handler/__init__.py
pcap_handler/pcapall.py
pcap_handler-0.1.3.dist-info/METADATA
pcap_handler-0.1.3.dist-info/WHEEL
pcap_handler-0.1.3.dist-info/top_level.txt
pcap_handler-0.1.3.dist-info/RECORD
