Metadata-Version: 2.1
Name: pcap-handler
Version: 0.1.3
Summary: Convert a pcap file into pandas DataFrame or CSV
Home-page: https://pcap_all.readthedocs.io/
Author: Aman Srivastava
Author-email: contact@amanonearth.com
License: MIT
Classifier: Intended Audience :: Developers
Classifier: License :: OSI Approved :: MIT License
Classifier: Programming Language :: Python
Classifier: Programming Language :: Python :: 3.6
Classifier: Programming Language :: Python :: 3.7
Classifier: Programming Language :: Python :: 3.8
Classifier: Programming Language :: Python :: 3.9
Classifier: Operating System :: OS Independent
Requires-Dist: numpy
Requires-Dist: pandas
